{"nodes": [{"id": "c_users_adisi_downloads_openinsight_tests_test_vectorstore_types_py", "label": "test_vectorstore_types.py", "file_type": "code", "type": "FUNCTION", "source_file": "C:\\Users\\adisi\\Downloads\\openinsight\\tests\\test_vectorstore_types.py", "source_location": "L1", "complexity": 1, "loc": 1}, {"id": "test_vectorstore_types_testsparsevectorconstruction", "label": "TestSparseVectorConstruction", "file_type": "code", "type": "CLASS", "source_file": "C:\\Users\\adisi\\Downloads\\openinsight\\tests\\test_vectorstore_types.py", "source_location": "L34", "complexity": 1, "loc": 23}, {"id": "test_vectorstore_types_testsparsevectorconstruction_test_valid_construction", "label": ".test_valid_construction()", "file_type": "code", "type": "FUNCTION", "source_file": "C:\\Users\\adisi\\Downloads\\openinsight\\tests\\test_vectorstore_types.py", "source_location": "L35", "complexity": 1, "loc": 4}, {"id": "test_vectorstore_types_testsparsevectorconstruction_test_empty_construction", "label": ".test_empty_construction()", "file_type": "code", "type": "FUNCTION", "source_file": "C:\\Users\\adisi\\Downloads\\openinsight\\tests\\test_vectorstore_types.py", "source_location": "L40", "complexity": 1, "loc": 4}, {"id": "test_vectorstore_types_testsparsevectorconstruction_test_mismatched_lengths_raise", "label": ".test_mismatched_lengths_raise()", "file_type": "code", "type": "FUNCTION", "source_file": "C:\\Users\\adisi\\Downloads\\openinsight\\tests\\test_vectorstore_types.py", "source_location": "L45", "complexity": 1, "loc": 3}, {"id": "test_vectorstore_types_testsparsevectorconstruction_test_mismatched_lengths_error_message_contains_counts", "label": ".test_mismatched_lengths_error_message_contains_counts()", "file_type": "code", "type": "FUNCTION", "source_file": "C:\\Users\\adisi\\Downloads\\openinsight\\tests\\test_vectorstore_types.py", "source_location": "L49", "complexity": 1, "loc": 3}, {"id": "test_vectorstore_types_testsparsevectorconstruction_test_single_element", "label": ".test_single_element()", "file_type": "code", "type": "FUNCTION", "source_file": "C:\\Users\\adisi\\Downloads\\openinsight\\tests\\test_vectorstore_types.py", "source_location": "L53", "complexity": 1, "loc": 4}, {"id": "test_vectorstore_types_testsparsevectorisempty", "label": "TestSparseVectorIsEmpty", "file_type": "code", "type": "CLASS", "source_file": "C:\\Users\\adisi\\Downloads\\openinsight\\tests\\test_vectorstore_types.py", "source_location": "L64", "complexity": 1, "loc": 11}, {"id": "test_vectorstore_types_testsparsevectorisempty_test_empty_vector_is_empty", "label": ".test_empty_vector_is_empty()", "file_type": "code", "type": "FUNCTION", "source_file": "C:\\Users\\adisi\\Downloads\\openinsight\\tests\\test_vectorstore_types.py", "source_location": "L65", "complexity": 1, "loc": 2}, {"id": "test_vectorstore_types_testsparsevectorisempty_test_non_empty_vector_not_empty", "label": ".test_non_empty_vector_not_empty()", "file_type": "code", "type": "FUNCTION", "source_file": "C:\\Users\\adisi\\Downloads\\openinsight\\tests\\test_vectorstore_types.py", "source_location": "L68", "complexity": 1, "loc": 3}, {"id": "test_vectorstore_types_testsparsevectorisempty_test_multi_element_not_empty", "label": ".test_multi_element_not_empty()", "file_type": "code", "type": "FUNCTION", "source_file": "C:\\Users\\adisi\\Downloads\\openinsight\\tests\\test_vectorstore_types.py", "source_location": "L72", "complexity": 1, "loc": 3}, {"id": "test_vectorstore_types_testsparsevectorroundtrip", "label": "TestSparseVectorRoundTrip", "file_type": "code", "type": "CLASS", "source_file": "C:\\Users\\adisi\\Downloads\\openinsight\\tests\\test_vectorstore_types.py", "source_location": "L82", "complexity": 1, "loc": 38}, {"id": "test_vectorstore_types_testsparsevectorroundtrip_test_to_mapping_basic", "label": ".test_to_mapping_basic()", "file_type": "code", "type": "FUNCTION", "source_file": "C:\\Users\\adisi\\Downloads\\openinsight\\tests\\test_vectorstore_types.py", "source_location": "L83", "complexity": 1, "loc": 3}, {"id": "test_vectorstore_types_testsparsevectorroundtrip_test_to_mapping_empty", "label": ".test_to_mapping_empty()", "file_type": "code", "type": "FUNCTION", "source_file": "C:\\Users\\adisi\\Downloads\\openinsight\\tests\\test_vectorstore_types.py", "source_location": "L87", "complexity": 1, "loc": 2}, {"id": "test_vectorstore_types_testsparsevectorroundtrip_test_from_mapping_basic", "label": ".test_from_mapping_basic()", "file_type": "code", "type": "FUNCTION", "source_file": "C:\\Users\\adisi\\Downloads\\openinsight\\tests\\test_vectorstore_types.py", "source_location": "L90", "complexity": 1, "loc": 6}, {"id": "test_vectorstore_types_testsparsevectorroundtrip_test_from_mapping_empty", "label": ".test_from_mapping_empty()", "file_type": "code", "type": "FUNCTION", "source_file": "C:\\Users\\adisi\\Downloads\\openinsight\\tests\\test_vectorstore_types.py", "source_location": "L97", "complexity": 1, "loc": 5}, {"id": "test_vectorstore_types_testsparsevectorroundtrip_test_round_trip_mapping", "label": ".test_round_trip_mapping()", "file_type": "code", "type": "FUNCTION", "source_file": "C:\\Users\\adisi\\Downloads\\openinsight\\tests\\test_vectorstore_types.py", "source_location": "L103", "complexity": 1, "loc": 5}, {"id": "test_vectorstore_types_testsparsevectorroundtrip_test_from_mapping_type_coercion", "label": ".test_from_mapping_type_coercion()", "file_type": "code", "type": "FUNCTION", "source_file": "C:\\Users\\adisi\\Downloads\\openinsight\\tests\\test_vectorstore_types.py", "source_location": "L109", "complexity": 1, "loc": 5}, {"id": "test_vectorstore_types_testsparsevectorroundtrip_test_to_mapping_type_coercion", "label": ".test_to_mapping_type_coercion()", "file_type": "code", "type": "FUNCTION", "source_file": "C:\\Users\\adisi\\Downloads\\openinsight\\tests\\test_vectorstore_types.py", "source_location": "L115", "complexity": 1, "loc": 5}, {"id": "test_vectorstore_types_testsparsevectorfromindexvalues", "label": "TestSparseVectorFromIndexValues", "file_type": "code", "type": "CLASS", "source_file": "C:\\Users\\adisi\\Downloads\\openinsight\\tests\\test_vectorstore_types.py", "source_location": "L127", "complexity": 1, "loc": 18}, {"id": "test_vectorstore_types_testsparsevectorfromindexvalues_test_basic", "label": ".test_basic()", "file_type": "code", "type": "FUNCTION", "source_file": "C:\\Users\\adisi\\Downloads\\openinsight\\tests\\test_vectorstore_types.py", "source_location": "L128", "complexity": 1, "loc": 4}, {"id": "test_vectorstore_types_testsparsevectorfromindexvalues_test_type_coercion", "label": ".test_type_coercion()", "file_type": "code", "type": "FUNCTION", "source_file": "C:\\Users\\adisi\\Downloads\\openinsight\\tests\\test_vectorstore_types.py", "source_location": "L133", "complexity": 1, "loc": 4}, {"id": "test_vectorstore_types_testsparsevectorfromindexvalues_test_mismatched_lengths_raise", "label": ".test_mismatched_lengths_raise()", "file_type": "code", "type": "FUNCTION", "source_file": "C:\\Users\\adisi\\Downloads\\openinsight\\tests\\test_vectorstore_types.py", "source_location": "L138", "complexity": 1, "loc": 3}, {"id": "test_vectorstore_types_testsparsevectorfromindexvalues_test_empty", "label": ".test_empty()", "file_type": "code", "type": "FUNCTION", "source_file": "C:\\Users\\adisi\\Downloads\\openinsight\\tests\\test_vectorstore_types.py", "source_location": "L142", "complexity": 1, "loc": 3}, {"id": "test_vectorstore_types_testfilterconditionhelpers", "label": "TestFilterConditionHelpers", "file_type": "code", "type": "CLASS", "source_file": "C:\\Users\\adisi\\Downloads\\openinsight\\tests\\test_vectorstore_types.py", "source_location": "L152", "complexity": 1, "loc": 32}, {"id": "test_vectorstore_types_testfilterconditionhelpers_test_eq", "label": ".test_eq()", "file_type": "code", "type": "FUNCTION", "source_file": "C:\\Users\\adisi\\Downloads\\openinsight\\tests\\test_vectorstore_types.py", "source_location": "L153", "complexity": 1, "loc": 5}, {"id": "test_vectorstore_types_testfilterconditionhelpers_test_in_values", "label": ".test_in_values()", "file_type": "code", "type": "FUNCTION", "source_file": "C:\\Users\\adisi\\Downloads\\openinsight\\tests\\test_vectorstore_types.py", "source_location": "L159", "complexity": 1, "loc": 4}, {"id": "test_vectorstore_types_testfilterconditionhelpers_test_gt", "label": ".test_gt()", "file_type": "code", "type": "FUNCTION", "source_file": "C:\\Users\\adisi\\Downloads\\openinsight\\tests\\test_vectorstore_types.py", "source_location": "L164", "complexity": 1, "loc": 3}, {"id": "test_vectorstore_types_testfilterconditionhelpers_test_gte", "label": ".test_gte()", "file_type": "code", "type": "FUNCTION", "source_file": "C:\\Users\\adisi\\Downloads\\openinsight\\tests\\test_vectorstore_types.py", "source_location": "L168", "complexity": 1, "loc": 3}, {"id": "test_vectorstore_types_testfilterconditionhelpers_test_lt", "label": ".test_lt()", "file_type": "code", "type": "FUNCTION", "source_file": "C:\\Users\\adisi\\Downloads\\openinsight\\tests\\test_vectorstore_types.py", "source_location": "L172", "complexity": 1, "loc": 3}, {"id": "test_vectorstore_types_testfilterconditionhelpers_test_lte", "label": ".test_lte()", "file_type": "code", "type": "FUNCTION", "source_file": "C:\\Users\\adisi\\Downloads\\openinsight\\tests\\test_vectorstore_types.py", "source_location": "L176", "complexity": 1, "loc": 3}, {"id": "test_vectorstore_types_testfilterconditionhelpers_test_frozen", "label": ".test_frozen()", "file_type": "code", "type": "FUNCTION", "source_file": "C:\\Users\\adisi\\Downloads\\openinsight\\tests\\test_vectorstore_types.py", "source_location": "L180", "complexity": 1, "loc": 4}, {"id": "test_vectorstore_types_testfilterexpression", "label": "TestFilterExpression", "file_type": "code", "type": "CLASS", "source_file": "C:\\Users\\adisi\\Downloads\\openinsight\\tests\\test_vectorstore_types.py", "source_location": "L191", "complexity": 1, "loc": 24}, {"id": "test_vectorstore_types_testfilterexpression_test_empty_expression_is_empty", "label": ".test_empty_expression_is_empty()", "file_type": "code", "type": "FUNCTION", "source_file": "C:\\Users\\adisi\\Downloads\\openinsight\\tests\\test_vectorstore_types.py", "source_location": "L192", "complexity": 1, "loc": 3}, {"id": "test_vectorstore_types_testfilterexpression_test_non_empty_expression_not_empty", "label": ".test_non_empty_expression_not_empty()", "file_type": "code", "type": "FUNCTION", "source_file": "C:\\Users\\adisi\\Downloads\\openinsight\\tests\\test_vectorstore_types.py", "source_location": "L196", "complexity": 1, "loc": 3}, {"id": "test_vectorstore_types_testfilterexpression_test_from_conditions", "label": ".test_from_conditions()", "file_type": "code", "type": "FUNCTION", "source_file": "C:\\Users\\adisi\\Downloads\\openinsight\\tests\\test_vectorstore_types.py", "source_location": "L200", "complexity": 1, "loc": 6}, {"id": "test_vectorstore_types_testfilterexpression_test_from_conditions_empty", "label": ".test_from_conditions_empty()", "file_type": "code", "type": "FUNCTION", "source_file": "C:\\Users\\adisi\\Downloads\\openinsight\\tests\\test_vectorstore_types.py", "source_location": "L207", "complexity": 1, "loc": 3}, {"id": "test_vectorstore_types_testfilterexpression_test_frozen", "label": ".test_frozen()", "file_type": "code", "type": "FUNCTION", "source_file": "C:\\Users\\adisi\\Downloads\\openinsight\\tests\\test_vectorstore_types.py", "source_location": "L211", "complexity": 1, "loc": 4}, {"id": "test_vectorstore_types_testvectorpoint", "label": "TestVectorPoint", "file_type": "code", "type": "CLASS", "source_file": "C:\\Users\\adisi\\Downloads\\openinsight\\tests\\test_vectorstore_types.py", "source_location": "L222", "complexity": 1, "loc": 20}, {"id": "test_vectorstore_types_testvectorpoint_test_construction", "label": ".test_construction()", "file_type": "code", "type": "FUNCTION", "source_file": "C:\\Users\\adisi\\Downloads\\openinsight\\tests\\test_vectorstore_types.py", "source_location": "L223", "complexity": 1, "loc": 10}, {"id": "test_vectorstore_types_testvectorpoint_test_none_sparse_vector", "label": ".test_none_sparse_vector()", "file_type": "code", "type": "FUNCTION", "source_file": "C:\\Users\\adisi\\Downloads\\openinsight\\tests\\test_vectorstore_types.py", "source_location": "L234", "complexity": 1, "loc": 8}, {"id": "test_vectorstore_types_testscoredpoint", "label": "TestScoredPoint", "file_type": "code", "type": "CLASS", "source_file": "C:\\Users\\adisi\\Downloads\\openinsight\\tests\\test_vectorstore_types.py", "source_location": "L244", "complexity": 1, "loc": 11}, {"id": "test_vectorstore_types_testscoredpoint_test_construction", "label": ".test_construction()", "file_type": "code", "type": "FUNCTION", "source_file": "C:\\Users\\adisi\\Downloads\\openinsight\\tests\\test_vectorstore_types.py", "source_location": "L245", "complexity": 1, "loc": 10}, {"id": "test_vectorstore_types_rationale_1", "label": "Unit tests for src/vectorstore/types.py and src/vectorstore/filters.py.  Covers:", "file_type": "rationale", "source_file": "C:\\Users\\adisi\\Downloads\\openinsight\\tests\\test_vectorstore_types.py", "source_location": "L1"}], "edges": [{"source": "c_users_adisi_downloads_openinsight_tests_test_vectorstore_types_py", "target": "pytest", "relation": "imports", "confidence": "EXTRACTED", "source_file": "C:\\Users\\adisi\\Downloads\\openinsight\\tests\\test_vectorstore_types.py", "source_location": "L13", "weight": 1.0}, {"source": "c_users_adisi_downloads_openinsight_tests_test_vectorstore_types_py", "target": "src_vectorstore_types", "relation": "imports_from", "confidence": "EXTRACTED", "source_file": "C:\\Users\\adisi\\Downloads\\openinsight\\tests\\test_vectorstore_types.py", "source_location": "L15", "weight": 1.0}, {"source": "c_users_adisi_downloads_openinsight_tests_test_vectorstore_types_py", "target": "src_vectorstore_filters", "relation": "imports_from", "confidence": "EXTRACTED", "source_file": "C:\\Users\\adisi\\Downloads\\openinsight\\tests\\test_vectorstore_types.py", "source_location": "L16", "weight": 1.0}, {"source": "c_users_adisi_downloads_openinsight_tests_test_vectorstore_types_py", "target": "test_vectorstore_types_testsparsevectorconstruction", "relation": "contains", "confidence": "EXTRACTED", "source_file": "C:\\Users\\adisi\\Downloads\\openinsight\\tests\\test_vectorstore_types.py", "source_location": "L34", "weight": 1.0}, {"source": "test_vectorstore_types_testsparsevectorconstruction", "target": "test_vectorstore_types_testsparsevectorconstruction_test_valid_construction", "relation": "method", "confidence": "EXTRACTED", "source_file": "C:\\Users\\adisi\\Downloads\\openinsight\\tests\\test_vectorstore_types.py", "source_location": "L35", "weight": 1.0}, {"source": "test_vectorstore_types_testsparsevectorconstruction", "target": "test_vectorstore_types_testsparsevectorconstruction_test_empty_construction", "relation": "method", "confidence": "EXTRACTED", "source_file": "C:\\Users\\adisi\\Downloads\\openinsight\\tests\\test_vectorstore_types.py", "source_location": "L40", "weight": 1.0}, {"source": "test_vectorstore_types_testsparsevectorconstruction", "target": "test_vectorstore_types_testsparsevectorconstruction_test_mismatched_lengths_raise", "relation": "method", "confidence": "EXTRACTED", "source_file": "C:\\Users\\adisi\\Downloads\\openinsight\\tests\\test_vectorstore_types.py", "source_location": "L45", "weight": 1.0}, {"source": "test_vectorstore_types_testsparsevectorconstruction", "target": "test_vectorstore_types_testsparsevectorconstruction_test_mismatched_lengths_error_message_contains_counts", "relation": "method", "confidence": "EXTRACTED", "source_file": "C:\\Users\\adisi\\Downloads\\openinsight\\tests\\test_vectorstore_types.py", "source_location": "L49", "weight": 1.0}, {"source": "test_vectorstore_types_testsparsevectorconstruction", "target": "test_vectorstore_types_testsparsevectorconstruction_test_single_element", "relation": "method", "confidence": "EXTRACTED", "source_file": "C:\\Users\\adisi\\Downloads\\openinsight\\tests\\test_vectorstore_types.py", "source_location": "L53", "weight": 1.0}, {"source": "c_users_adisi_downloads_openinsight_tests_test_vectorstore_types_py", "target": "test_vectorstore_types_testsparsevectorisempty", "relation": "contains", "confidence": "EXTRACTED", "source_file": "C:\\Users\\adisi\\Downloads\\openinsight\\tests\\test_vectorstore_types.py", "source_location": "L64", "weight": 1.0}, {"source": "test_vectorstore_types_testsparsevectorisempty", "target": "test_vectorstore_types_testsparsevectorisempty_test_empty_vector_is_empty", "relation": "method", "confidence": "EXTRACTED", "source_file": "C:\\Users\\adisi\\Downloads\\openinsight\\tests\\test_vectorstore_types.py", "source_location": "L65", "weight": 1.0}, {"source": "test_vectorstore_types_testsparsevectorisempty", "target": "test_vectorstore_types_testsparsevectorisempty_test_non_empty_vector_not_empty", "relation": "method", "confidence": "EXTRACTED", "source_file": "C:\\Users\\adisi\\Downloads\\openinsight\\tests\\test_vectorstore_types.py", "source_location": "L68", "weight": 1.0}, {"source": "test_vectorstore_types_testsparsevectorisempty", "target": "test_vectorstore_types_testsparsevectorisempty_test_multi_element_not_empty", "relation": "method", "confidence": "EXTRACTED", "source_file": "C:\\Users\\adisi\\Downloads\\openinsight\\tests\\test_vectorstore_types.py", "source_location": "L72", "weight": 1.0}, {"source": "c_users_adisi_downloads_openinsight_tests_test_vectorstore_types_py", "target": "test_vectorstore_types_testsparsevectorroundtrip", "relation": "contains", "confidence": "EXTRACTED", "source_file": "C:\\Users\\adisi\\Downloads\\openinsight\\tests\\test_vectorstore_types.py", "source_location": "L82", "weight": 1.0}, {"source": "test_vectorstore_types_testsparsevectorroundtrip", "target": "test_vectorstore_types_testsparsevectorroundtrip_test_to_mapping_basic", "relation": "method", "confidence": "EXTRACTED", "source_file": "C:\\Users\\adisi\\Downloads\\openinsight\\tests\\test_vectorstore_types.py", "source_location": "L83", "weight": 1.0}, {"source": "test_vectorstore_types_testsparsevectorroundtrip", "target": "test_vectorstore_types_testsparsevectorroundtrip_test_to_mapping_empty", "relation": "method", "confidence": "EXTRACTED", "source_file": "C:\\Users\\adisi\\Downloads\\openinsight\\tests\\test_vectorstore_types.py", "source_location": "L87", "weight": 1.0}, {"source": "test_vectorstore_types_testsparsevectorroundtrip", "target": "test_vectorstore_types_testsparsevectorroundtrip_test_from_mapping_basic", "relation": "method", "confidence": "EXTRACTED", "source_file": "C:\\Users\\adisi\\Downloads\\openinsight\\tests\\test_vectorstore_types.py", "source_location": "L90", "weight": 1.0}, {"source": "test_vectorstore_types_testsparsevectorroundtrip", "target": "test_vectorstore_types_testsparsevectorroundtrip_test_from_mapping_empty", "relation": "method", "confidence": "EXTRACTED", "source_file": "C:\\Users\\adisi\\Downloads\\openinsight\\tests\\test_vectorstore_types.py", "source_location": "L97", "weight": 1.0}, {"source": "test_vectorstore_types_testsparsevectorroundtrip", "target": "test_vectorstore_types_testsparsevectorroundtrip_test_round_trip_mapping", "relation": "method", "confidence": "EXTRACTED", "source_file": "C:\\Users\\adisi\\Downloads\\openinsight\\tests\\test_vectorstore_types.py", "source_location": "L103", "weight": 1.0}, {"source": "test_vectorstore_types_testsparsevectorroundtrip", "target": "test_vectorstore_types_testsparsevectorroundtrip_test_from_mapping_type_coercion", "relation": "method", "confidence": "EXTRACTED", "source_file": "C:\\Users\\adisi\\Downloads\\openinsight\\tests\\test_vectorstore_types.py", "source_location": "L109", "weight": 1.0}, {"source": "test_vectorstore_types_testsparsevectorroundtrip", "target": "test_vectorstore_types_testsparsevectorroundtrip_test_to_mapping_type_coercion", "relation": "method", "confidence": "EXTRACTED", "source_file": "C:\\Users\\adisi\\Downloads\\openinsight\\tests\\test_vectorstore_types.py", "source_location": "L115", "weight": 1.0}, {"source": "c_users_adisi_downloads_openinsight_tests_test_vectorstore_types_py", "target": "test_vectorstore_types_testsparsevectorfromindexvalues", "relation": "contains", "confidence": "EXTRACTED", "source_file": "C:\\Users\\adisi\\Downloads\\openinsight\\tests\\test_vectorstore_types.py", "source_location": "L127", "weight": 1.0}, {"source": "test_vectorstore_types_testsparsevectorfromindexvalues", "target": "test_vectorstore_types_testsparsevectorfromindexvalues_test_basic", "relation": "method", "confidence": "EXTRACTED", "source_file": "C:\\Users\\adisi\\Downloads\\openinsight\\tests\\test_vectorstore_types.py", "source_location": "L128", "weight": 1.0}, {"source": "test_vectorstore_types_testsparsevectorfromindexvalues", "target": "test_vectorstore_types_testsparsevectorfromindexvalues_test_type_coercion", "relation": "method", "confidence": "EXTRACTED", "source_file": "C:\\Users\\adisi\\Downloads\\openinsight\\tests\\test_vectorstore_types.py", "source_location": "L133", "weight": 1.0}, {"source": "test_vectorstore_types_testsparsevectorfromindexvalues", "target": "test_vectorstore_types_testsparsevectorfromindexvalues_test_mismatched_lengths_raise", "relation": "method", "confidence": "EXTRACTED", "source_file": "C:\\Users\\adisi\\Downloads\\openinsight\\tests\\test_vectorstore_types.py", "source_location": "L138", "weight": 1.0}, {"source": "test_vectorstore_types_testsparsevectorfromindexvalues", "target": "test_vectorstore_types_testsparsevectorfromindexvalues_test_empty", "relation": "method", "confidence": "EXTRACTED", "source_file": "C:\\Users\\adisi\\Downloads\\openinsight\\tests\\test_vectorstore_types.py", "source_location": "L142", "weight": 1.0}, {"source": "c_users_adisi_downloads_openinsight_tests_test_vectorstore_types_py", "target": "test_vectorstore_types_testfilterconditionhelpers", "relation": "contains", "confidence": "EXTRACTED", "source_file": "C:\\Users\\adisi\\Downloads\\openinsight\\tests\\test_vectorstore_types.py", "source_location": "L152", "weight": 1.0}, {"source": "test_vectorstore_types_testfilterconditionhelpers", "target": "test_vectorstore_types_testfilterconditionhelpers_test_eq", "relation": "method", "confidence": "EXTRACTED", "source_file": "C:\\Users\\adisi\\Downloads\\openinsight\\tests\\test_vectorstore_types.py", "source_location": "L153", "weight": 1.0}, {"source": "test_vectorstore_types_testfilterconditionhelpers", "target": "test_vectorstore_types_testfilterconditionhelpers_test_in_values", "relation": "method", "confidence": "EXTRACTED", "source_file": "C:\\Users\\adisi\\Downloads\\openinsight\\tests\\test_vectorstore_types.py", "source_location": "L159", "weight": 1.0}, {"source": "test_vectorstore_types_testfilterconditionhelpers", "target": "test_vectorstore_types_testfilterconditionhelpers_test_gt", "relation": "method", "confidence": "EXTRACTED", "source_file": "C:\\Users\\adisi\\Downloads\\openinsight\\tests\\test_vectorstore_types.py", "source_location": "L164", "weight": 1.0}, {"source": "test_vectorstore_types_testfilterconditionhelpers", "target": "test_vectorstore_types_testfilterconditionhelpers_test_gte", "relation": "method", "confidence": "EXTRACTED", "source_file": "C:\\Users\\adisi\\Downloads\\openinsight\\tests\\test_vectorstore_types.py", "source_location": "L168", "weight": 1.0}, {"source": "test_vectorstore_types_testfilterconditionhelpers", "target": "test_vectorstore_types_testfilterconditionhelpers_test_lt", "relation": "method", "confidence": "EXTRACTED", "source_file": "C:\\Users\\adisi\\Downloads\\openinsight\\tests\\test_vectorstore_types.py", "source_location": "L172", "weight": 1.0}, {"source": "test_vectorstore_types_testfilterconditionhelpers", "target": "test_vectorstore_types_testfilterconditionhelpers_test_lte", "relation": "method", "confidence": "EXTRACTED", "source_file": "C:\\Users\\adisi\\Downloads\\openinsight\\tests\\test_vectorstore_types.py", "source_location": "L176", "weight": 1.0}, {"source": "test_vectorstore_types_testfilterconditionhelpers", "target": "test_vectorstore_types_testfilterconditionhelpers_test_frozen", "relation": "method", "confidence": "EXTRACTED", "source_file": "C:\\Users\\adisi\\Downloads\\openinsight\\tests\\test_vectorstore_types.py", "source_location": "L180", "weight": 1.0}, {"source": "c_users_adisi_downloads_openinsight_tests_test_vectorstore_types_py", "target": "test_vectorstore_types_testfilterexpression", "relation": "contains", "confidence": "EXTRACTED", "source_file": "C:\\Users\\adisi\\Downloads\\openinsight\\tests\\test_vectorstore_types.py", "source_location": "L191", "weight": 1.0}, {"source": "test_vectorstore_types_testfilterexpression", "target": "test_vectorstore_types_testfilterexpression_test_empty_expression_is_empty", "relation": "method", "confidence": "EXTRACTED", "source_file": "C:\\Users\\adisi\\Downloads\\openinsight\\tests\\test_vectorstore_types.py", "source_location": "L192", "weight": 1.0}, {"source": "test_vectorstore_types_testfilterexpression", "target": "test_vectorstore_types_testfilterexpression_test_non_empty_expression_not_empty", "relation": "method", "confidence": "EXTRACTED", "source_file": "C:\\Users\\adisi\\Downloads\\openinsight\\tests\\test_vectorstore_types.py", "source_location": "L196", "weight": 1.0}, {"source": "test_vectorstore_types_testfilterexpression", "target": "test_vectorstore_types_testfilterexpression_test_from_conditions", "relation": "method", "confidence": "EXTRACTED", "source_file": "C:\\Users\\adisi\\Downloads\\openinsight\\tests\\test_vectorstore_types.py", "source_location": "L200", "weight": 1.0}, {"source": "test_vectorstore_types_testfilterexpression", "target": "test_vectorstore_types_testfilterexpression_test_from_conditions_empty", "relation": "method", "confidence": "EXTRACTED", "source_file": "C:\\Users\\adisi\\Downloads\\openinsight\\tests\\test_vectorstore_types.py", "source_location": "L207", "weight": 1.0}, {"source": "test_vectorstore_types_testfilterexpression", "target": "test_vectorstore_types_testfilterexpression_test_frozen", "relation": "method", "confidence": "EXTRACTED", "source_file": "C:\\Users\\adisi\\Downloads\\openinsight\\tests\\test_vectorstore_types.py", "source_location": "L211", "weight": 1.0}, {"source": "c_users_adisi_downloads_openinsight_tests_test_vectorstore_types_py", "target": "test_vectorstore_types_testvectorpoint", "relation": "contains", "confidence": "EXTRACTED", "source_file": "C:\\Users\\adisi\\Downloads\\openinsight\\tests\\test_vectorstore_types.py", "source_location": "L222", "weight": 1.0}, {"source": "test_vectorstore_types_testvectorpoint", "target": "test_vectorstore_types_testvectorpoint_test_construction", "relation": "method", "confidence": "EXTRACTED", "source_file": "C:\\Users\\adisi\\Downloads\\openinsight\\tests\\test_vectorstore_types.py", "source_location": "L223", "weight": 1.0}, {"source": "test_vectorstore_types_testvectorpoint", "target": "test_vectorstore_types_testvectorpoint_test_none_sparse_vector", "relation": "method", "confidence": "EXTRACTED", "source_file": "C:\\Users\\adisi\\Downloads\\openinsight\\tests\\test_vectorstore_types.py", "source_location": "L234", "weight": 1.0}, {"source": "c_users_adisi_downloads_openinsight_tests_test_vectorstore_types_py", "target": "test_vectorstore_types_testscoredpoint", "relation": "contains", "confidence": "EXTRACTED", "source_file": "C:\\Users\\adisi\\Downloads\\openinsight\\tests\\test_vectorstore_types.py", "source_location": "L244", "weight": 1.0}, {"source": "test_vectorstore_types_testscoredpoint", "target": "test_vectorstore_types_testscoredpoint_test_construction", "relation": "method", "confidence": "EXTRACTED", "source_file": "C:\\Users\\adisi\\Downloads\\openinsight\\tests\\test_vectorstore_types.py", "source_location": "L245", "weight": 1.0}, {"source": "test_vectorstore_types_rationale_1", "target": "c_users_adisi_downloads_openinsight_tests_test_vectorstore_types_py", "relation": "rationale_for", "confidence": "EXTRACTED", "source_file": "C:\\Users\\adisi\\Downloads\\openinsight\\tests\\test_vectorstore_types.py", "source_location": "L1", "weight": 1.0}], "raw_calls": [{"caller_nid": "test_vectorstore_types_testsparsevectorconstruction_test_valid_construction", "callee": "SparseVector", "source_file": "C:\\Users\\adisi\\Downloads\\openinsight\\tests\\test_vectorstore_types.py", "source_location": "L36"}, {"caller_nid": "test_vectorstore_types_testsparsevectorconstruction_test_empty_construction", "callee": "SparseVector", "source_file": "C:\\Users\\adisi\\Downloads\\openinsight\\tests\\test_vectorstore_types.py", "source_location": "L41"}, {"caller_nid": "test_vectorstore_types_testsparsevectorconstruction_test_mismatched_lengths_raise", "callee": "raises", "source_file": "C:\\Users\\adisi\\Downloads\\openinsight\\tests\\test_vectorstore_types.py", "source_location": "L46"}, {"caller_nid": "test_vectorstore_types_testsparsevectorconstruction_test_mismatched_lengths_raise", "callee": "SparseVector", "source_file": "C:\\Users\\adisi\\Downloads\\openinsight\\tests\\test_vectorstore_types.py", "source_location": "L47"}, {"caller_nid": "test_vectorstore_types_testsparsevectorconstruction_test_mismatched_lengths_error_message_contains_counts", "callee": "raises", "source_file": "C:\\Users\\adisi\\Downloads\\openinsight\\tests\\test_vectorstore_types.py", "source_location": "L50"}, {"caller_nid": "test_vectorstore_types_testsparsevectorconstruction_test_mismatched_lengths_error_message_contains_counts", "callee": "SparseVector", "source_file": "C:\\Users\\adisi\\Downloads\\openinsight\\tests\\test_vectorstore_types.py", "source_location": "L51"}, {"caller_nid": "test_vectorstore_types_testsparsevectorconstruction_test_single_element", "callee": "SparseVector", "source_file": "C:\\Users\\adisi\\Downloads\\openinsight\\tests\\test_vectorstore_types.py", "source_location": "L54"}, {"caller_nid": "test_vectorstore_types_testsparsevectorisempty_test_empty_vector_is_empty", "callee": "is_empty", "source_file": "C:\\Users\\adisi\\Downloads\\openinsight\\tests\\test_vectorstore_types.py", "source_location": "L66"}, {"caller_nid": "test_vectorstore_types_testsparsevectorisempty_test_empty_vector_is_empty", "callee": "SparseVector", "source_file": "C:\\Users\\adisi\\Downloads\\openinsight\\tests\\test_vectorstore_types.py", "source_location": "L66"}, {"caller_nid": "test_vectorstore_types_testsparsevectorisempty_test_non_empty_vector_not_empty", "callee": "SparseVector", "source_file": "C:\\Users\\adisi\\Downloads\\openinsight\\tests\\test_vectorstore_types.py", "source_location": "L69"}, {"caller_nid": "test_vectorstore_types_testsparsevectorisempty_test_non_empty_vector_not_empty", "callee": "is_empty", "source_file": "C:\\Users\\adisi\\Downloads\\openinsight\\tests\\test_vectorstore_types.py", "source_location": "L70"}, {"caller_nid": "test_vectorstore_types_testsparsevectorisempty_test_multi_element_not_empty", "callee": "SparseVector", "source_file": "C:\\Users\\adisi\\Downloads\\openinsight\\tests\\test_vectorstore_types.py", "source_location": "L73"}, {"caller_nid": "test_vectorstore_types_testsparsevectorisempty_test_multi_element_not_empty", "callee": "is_empty", "source_file": "C:\\Users\\adisi\\Downloads\\openinsight\\tests\\test_vectorstore_types.py", "source_location": "L74"}, {"caller_nid": "test_vectorstore_types_testsparsevectorroundtrip_test_to_mapping_basic", "callee": "SparseVector", "source_file": "C:\\Users\\adisi\\Downloads\\openinsight\\tests\\test_vectorstore_types.py", "source_location": "L84"}, {"caller_nid": "test_vectorstore_types_testsparsevectorroundtrip_test_to_mapping_basic", "callee": "to_mapping", "source_file": "C:\\Users\\adisi\\Downloads\\openinsight\\tests\\test_vectorstore_types.py", "source_location": "L85"}, {"caller_nid": "test_vectorstore_types_testsparsevectorroundtrip_test_to_mapping_empty", "callee": "to_mapping", "source_file": "C:\\Users\\adisi\\Downloads\\openinsight\\tests\\test_vectorstore_types.py", "source_location": "L88"}, {"caller_nid": "test_vectorstore_types_testsparsevectorroundtrip_test_to_mapping_empty", "callee": "SparseVector", "source_file": "C:\\Users\\adisi\\Downloads\\openinsight\\tests\\test_vectorstore_types.py", "source_location": "L88"}, {"caller_nid": "test_vectorstore_types_testsparsevectorroundtrip_test_from_mapping_basic", "callee": "from_mapping", "source_file": "C:\\Users\\adisi\\Downloads\\openinsight\\tests\\test_vectorstore_types.py", "source_location": "L92"}, {"caller_nid": "test_vectorstore_types_testsparsevectorroundtrip_test_from_mapping_empty", "callee": "from_mapping", "source_file": "C:\\Users\\adisi\\Downloads\\openinsight\\tests\\test_vectorstore_types.py", "source_location": "L98"}, {"caller_nid": "test_vectorstore_types_testsparsevectorroundtrip_test_from_mapping_empty", "callee": "is_empty", "source_file": "C:\\Users\\adisi\\Downloads\\openinsight\\tests\\test_vectorstore_types.py", "source_location": "L99"}, {"caller_nid": "test_vectorstore_types_testsparsevectorroundtrip_test_round_trip_mapping", "callee": "from_mapping", "source_file": "C:\\Users\\adisi\\Downloads\\openinsight\\tests\\test_vectorstore_types.py", "source_location": "L105"}, {"caller_nid": "test_vectorstore_types_testsparsevectorroundtrip_test_round_trip_mapping", "callee": "to_mapping", "source_file": "C:\\Users\\adisi\\Downloads\\openinsight\\tests\\test_vectorstore_types.py", "source_location": "L106"}, {"caller_nid": "test_vectorstore_types_testsparsevectorroundtrip_test_from_mapping_type_coercion", "callee": "from_mapping", "source_file": "C:\\Users\\adisi\\Downloads\\openinsight\\tests\\test_vectorstore_types.py", "source_location": "L111"}, {"caller_nid": "test_vectorstore_types_testsparsevectorroundtrip_test_to_mapping_type_coercion", "callee": "SparseVector", "source_file": "C:\\Users\\adisi\\Downloads\\openinsight\\tests\\test_vectorstore_types.py", "source_location": "L116"}, {"caller_nid": "test_vectorstore_types_testsparsevectorroundtrip_test_to_mapping_type_coercion", "callee": "to_mapping", "source_file": "C:\\Users\\adisi\\Downloads\\openinsight\\tests\\test_vectorstore_types.py", "source_location": "L117"}, {"caller_nid": "test_vectorstore_types_testsparsevectorroundtrip_test_to_mapping_type_coercion", "callee": "all", "source_file": "C:\\Users\\adisi\\Downloads\\openinsight\\tests\\test_vectorstore_types.py", "source_location": "L118"}, {"caller_nid": "test_vectorstore_types_testsparsevectorroundtrip_test_to_mapping_type_coercion", "callee": "isinstance", "source_file": "C:\\Users\\adisi\\Downloads\\openinsight\\tests\\test_vectorstore_types.py", "source_location": "L118"}, {"caller_nid": "test_vectorstore_types_testsparsevectorroundtrip_test_to_mapping_type_coercion", "callee": "all", "source_file": "C:\\Users\\adisi\\Downloads\\openinsight\\tests\\test_vectorstore_types.py", "source_location": "L119"}, {"caller_nid": "test_vectorstore_types_testsparsevectorroundtrip_test_to_mapping_type_coercion", "callee": "isinstance", "source_file": "C:\\Users\\adisi\\Downloads\\openinsight\\tests\\test_vectorstore_types.py", "source_location": "L119"}, {"caller_nid": "test_vectorstore_types_testsparsevectorroundtrip_test_to_mapping_type_coercion", "callee": "values", "source_file": "C:\\Users\\adisi\\Downloads\\openinsight\\tests\\test_vectorstore_types.py", "source_location": "L119"}, {"caller_nid": "test_vectorstore_types_testsparsevectorfromindexvalues_test_basic", "callee": "from_index_values", "source_file": "C:\\Users\\adisi\\Downloads\\openinsight\\tests\\test_vectorstore_types.py", "source_location": "L129"}, {"caller_nid": "test_vectorstore_types_testsparsevectorfromindexvalues_test_type_coercion", "callee": "from_index_values", "source_file": "C:\\Users\\adisi\\Downloads\\openinsight\\tests\\test_vectorstore_types.py", "source_location": "L134"}, {"caller_nid": "test_vectorstore_types_testsparsevectorfromindexvalues_test_type_coercion", "callee": "all", "source_file": "C:\\Users\\adisi\\Downloads\\openinsight\\tests\\test_vectorstore_types.py", "source_location": "L135"}, {"caller_nid": "test_vectorstore_types_testsparsevectorfromindexvalues_test_type_coercion", "callee": "isinstance", "source_file": "C:\\Users\\adisi\\Downloads\\openinsight\\tests\\test_vectorstore_types.py", "source_location": "L135"}, {"caller_nid": "test_vectorstore_types_testsparsevectorfromindexvalues_test_type_coercion", "callee": "all", "source_file": "C:\\Users\\adisi\\Downloads\\openinsight\\tests\\test_vectorstore_types.py", "source_location": "L136"}, {"caller_nid": "test_vectorstore_types_testsparsevectorfromindexvalues_test_type_coercion", "callee": "isinstance", "source_file": "C:\\Users\\adisi\\Downloads\\openinsight\\tests\\test_vectorstore_types.py", "source_location": "L136"}, {"caller_nid": "test_vectorstore_types_testsparsevectorfromindexvalues_test_mismatched_lengths_raise", "callee": "raises", "source_file": "C:\\Users\\adisi\\Downloads\\openinsight\\tests\\test_vectorstore_types.py", "source_location": "L139"}, {"caller_nid": "test_vectorstore_types_testsparsevectorfromindexvalues_test_mismatched_lengths_raise", "callee": "from_index_values", "source_file": "C:\\Users\\adisi\\Downloads\\openinsight\\tests\\test_vectorstore_types.py", "source_location": "L140"}, {"caller_nid": "test_vectorstore_types_testsparsevectorfromindexvalues_test_empty", "callee": "from_index_values", "source_file": "C:\\Users\\adisi\\Downloads\\openinsight\\tests\\test_vectorstore_types.py", "source_location": "L143"}, {"caller_nid": "test_vectorstore_types_testsparsevectorfromindexvalues_test_empty", "callee": "is_empty", "source_file": "C:\\Users\\adisi\\Downloads\\openinsight\\tests\\test_vectorstore_types.py", "source_location": "L144"}, {"caller_nid": "test_vectorstore_types_testfilterconditionhelpers_test_eq", "callee": "eq", "source_file": "C:\\Users\\adisi\\Downloads\\openinsight\\tests\\test_vectorstore_types.py", "source_location": "L154"}, {"caller_nid": "test_vectorstore_types_testfilterconditionhelpers_test_in_values", "callee": "in_values", "source_file": "C:\\Users\\adisi\\Downloads\\openinsight\\tests\\test_vectorstore_types.py", "source_location": "L160"}, {"caller_nid": "test_vectorstore_types_testfilterconditionhelpers_test_gt", "callee": "gt", "source_file": "C:\\Users\\adisi\\Downloads\\openinsight\\tests\\test_vectorstore_types.py", "source_location": "L165"}, {"caller_nid": "test_vectorstore_types_testfilterconditionhelpers_test_gte", "callee": "gte", "source_file": "C:\\Users\\adisi\\Downloads\\openinsight\\tests\\test_vectorstore_types.py", "source_location": "L169"}, {"caller_nid": "test_vectorstore_types_testfilterconditionhelpers_test_lt", "callee": "lt", "source_file": "C:\\Users\\adisi\\Downloads\\openinsight\\tests\\test_vectorstore_types.py", "source_location": "L173"}, {"caller_nid": "test_vectorstore_types_testfilterconditionhelpers_test_lte", "callee": "lte", "source_file": "C:\\Users\\adisi\\Downloads\\openinsight\\tests\\test_vectorstore_types.py", "source_location": "L177"}, {"caller_nid": "test_vectorstore_types_testfilterconditionhelpers_test_frozen", "callee": "eq", "source_file": "C:\\Users\\adisi\\Downloads\\openinsight\\tests\\test_vectorstore_types.py", "source_location": "L181"}, {"caller_nid": "test_vectorstore_types_testfilterconditionhelpers_test_frozen", "callee": "raises", "source_file": "C:\\Users\\adisi\\Downloads\\openinsight\\tests\\test_vectorstore_types.py", "source_location": "L182"}, {"caller_nid": "test_vectorstore_types_testfilterexpression_test_empty_expression_is_empty", "callee": "FilterExpression", "source_file": "C:\\Users\\adisi\\Downloads\\openinsight\\tests\\test_vectorstore_types.py", "source_location": "L193"}, {"caller_nid": "test_vectorstore_types_testfilterexpression_test_empty_expression_is_empty", "callee": "is_empty", "source_file": "C:\\Users\\adisi\\Downloads\\openinsight\\tests\\test_vectorstore_types.py", "source_location": "L194"}, {"caller_nid": "test_vectorstore_types_testfilterexpression_test_non_empty_expression_not_empty", "callee": "FilterExpression", "source_file": "C:\\Users\\adisi\\Downloads\\openinsight\\tests\\test_vectorstore_types.py", "source_location": "L197"}, {"caller_nid": "test_vectorstore_types_testfilterexpression_test_non_empty_expression_not_empty", "callee": "eq", "source_file": "C:\\Users\\adisi\\Downloads\\openinsight\\tests\\test_vectorstore_types.py", "source_location": "L197"}, {"caller_nid": "test_vectorstore_types_testfilterexpression_test_non_empty_expression_not_empty", "callee": "is_empty", "source_file": "C:\\Users\\adisi\\Downloads\\openinsight\\tests\\test_vectorstore_types.py", "source_location": "L198"}, {"caller_nid": "test_vectorstore_types_testfilterexpression_test_from_conditions", "callee": "eq", "source_file": "C:\\Users\\adisi\\Downloads\\openinsight\\tests\\test_vectorstore_types.py", "source_location": "L201"}, {"caller_nid": "test_vectorstore_types_testfilterexpression_test_from_conditions", "callee": "gt", "source_file": "C:\\Users\\adisi\\Downloads\\openinsight\\tests\\test_vectorstore_types.py", "source_location": "L201"}, {"caller_nid": "test_vectorstore_types_testfilterexpression_test_from_conditions", "callee": "from_conditions", "source_file": "C:\\Users\\adisi\\Downloads\\openinsight\\tests\\test_vectorstore_types.py", "source_location": "L202"}, {"caller_nid": "test_vectorstore_types_testfilterexpression_test_from_conditions", "callee": "len", "source_file": "C:\\Users\\adisi\\Downloads\\openinsight\\tests\\test_vectorstore_types.py", "source_location": "L203"}, {"caller_nid": "test_vectorstore_types_testfilterexpression_test_from_conditions", "callee": "eq", "source_file": "C:\\Users\\adisi\\Downloads\\openinsight\\tests\\test_vectorstore_types.py", "source_location": "L204"}, {"caller_nid": "test_vectorstore_types_testfilterexpression_test_from_conditions", "callee": "gt", "source_file": "C:\\Users\\adisi\\Downloads\\openinsight\\tests\\test_vectorstore_types.py", "source_location": "L205"}, {"caller_nid": "test_vectorstore_types_testfilterexpression_test_from_conditions_empty", "callee": "from_conditions", "source_file": "C:\\Users\\adisi\\Downloads\\openinsight\\tests\\test_vectorstore_types.py", "source_location": "L208"}, {"caller_nid": "test_vectorstore_types_testfilterexpression_test_from_conditions_empty", "callee": "is_empty", "source_file": "C:\\Users\\adisi\\Downloads\\openinsight\\tests\\test_vectorstore_types.py", "source_location": "L209"}, {"caller_nid": "test_vectorstore_types_testfilterexpression_test_frozen", "callee": "FilterExpression", "source_file": "C:\\Users\\adisi\\Downloads\\openinsight\\tests\\test_vectorstore_types.py", "source_location": "L212"}, {"caller_nid": "test_vectorstore_types_testfilterexpression_test_frozen", "callee": "raises", "source_file": "C:\\Users\\adisi\\Downloads\\openinsight\\tests\\test_vectorstore_types.py", "source_location": "L213"}, {"caller_nid": "test_vectorstore_types_testfilterexpression_test_frozen", "callee": "eq", "source_file": "C:\\Users\\adisi\\Downloads\\openinsight\\tests\\test_vectorstore_types.py", "source_location": "L214"}, {"caller_nid": "test_vectorstore_types_testvectorpoint_test_construction", "callee": "SparseVector", "source_file": "C:\\Users\\adisi\\Downloads\\openinsight\\tests\\test_vectorstore_types.py", "source_location": "L224"}, {"caller_nid": "test_vectorstore_types_testvectorpoint_test_construction", "callee": "VectorPoint", "source_file": "C:\\Users\\adisi\\Downloads\\openinsight\\tests\\test_vectorstore_types.py", "source_location": "L225"}, {"caller_nid": "test_vectorstore_types_testvectorpoint_test_none_sparse_vector", "callee": "VectorPoint", "source_file": "C:\\Users\\adisi\\Downloads\\openinsight\\tests\\test_vectorstore_types.py", "source_location": "L235"}, {"caller_nid": "test_vectorstore_types_testscoredpoint_test_construction", "callee": "ScoredPoint", "source_file": "C:\\Users\\adisi\\Downloads\\openinsight\\tests\\test_vectorstore_types.py", "source_location": "L246"}]}